{
  "projects": [
    {
      "title": "DGTL CTRL // BREAK",
      "category": "commercial",
      "year": "2026",
      "vimeo_id": "1170309766",
      "credits": {
        "Director": "Aaron van Valen",
        "DOP": "Zeger Verschuren"
      },
      "type": "Festival Film",
      "thumbnail": "assets/images/thumbnails/screenshot-2026-03-17-at-16.38.51.png",
      "thumbnail_url": "https://i.vimeocdn.com/video/2135017422-1fd51b55ef3454c4fcd22db109811b7d8bef7d991ab121e88ebab30122e945e7-d_640?region=us"
    },
    {
      "title": "Ikea",
      "category": "commercial",
      "type": "Commercial",
      "year": "2025",
      "vimeo_id": "https://vimeo.com/1170310615",
      "thumbnail": "assets/images/thumbnails/screenshot-2026-03-17-at-17.31.33.png",
      "credits": {
        "Director": "Jacobine van Hellemond",
        "Production": "Movie Magic International",
        "DOP": "Myrthe Mosterman",
        "Agency": "Ogilvy Italy"
      }
    },
    {
      "title": "Kruidvat",
      "category": "commercial",
      "type": "Commercial",
      "year": "2025",
      "thumbnail": "assets/images/thumbnails/screenshot-2026-03-17-at-16.08.10.png",
      "vimeo_id": "1173222103",
      "credits": {
        "Director": "Juliette Stevens",
        "Production": "Wefilm",
        "DOP": "Lennart Verstegen",
        "Agency": "DDB Amsterdam",
        "Colour Grade": "de Grot",
        "Music": "Jorrit Kleijnen en Jacob Meijer"
      },
      "thumbnail_url": "https://i.vimeocdn.com/video/2133367555-0579175868b3569312d74897ebd0a14bc03c6cec9988f8fdac364f2afbede7d9-d_640?region=us"
    },
    {
      "title": "Peggy",
      "category": "documentary",
      "type": "Short Film",
      "year": "2024",
      "vimeo_id": "1073861924",
      "thumbnail": "assets/images/thumbnails/peggy.jpg",
      "credits": {
        "Director": "Andreas Pasvantis",
        "DOP": "Katja van den Broeke",
        "Super 8 & Photography": "Andreas Pasvantis",
        "Music & Sound": "Diederik Idenburg",
        "Colour Grade": "Black Kite Studios",
        "Colourist": "Rich Fearon"
      },
      "thumbnail_url": "https://i.vimeocdn.com/video/2129056353-d8fe7da5b99e9c0221f3b74467e07200b3d6d085c1688c28a1996c496f5198cd-d_640?region=us"
    },
    {
      "title": "KWF",
      "category": "commercial",
      "type": "Commercial",
      "year": "2025",
      "vimeo_id": "1073864764",
      "thumbnail": "assets/images/thumbnails/kwf.jpg",
      "credits": {
        "Director": "Jacobine van Hellemond",
        "Production": "hazazaH",
        "Agency": "Monks",
        "DOP": "Katja van den Broeke",
        "Music": "Jet van der Steen, Jesper Hoekstra, Nienke Leone van der Velden",
        "Grade": "Joppo, De Grot"
      },
      "thumbnail_url": "https://i.vimeocdn.com/video/2129049326-e3189ec6e7d73958e53a8b1e930b625f6a5c08b0d5d5f1a317ce1e2393968265-d_640?region=us"
    },
    {
      "title": "Rabobank",
      "category": "commercial",
      "type": "Online Ad",
      "year": "2025",
      "vimeo_id": "1174414692",
      "credits": {
        "Director": "No Maybe Yes aka Max Pauwels",
        "Production": "Cake Film & Photo",
        "Agency": "Dentsu Creative"
      },
      "thumbnail": "assets/images/thumbnails/screenshot-2026-03-17-at-16.09.03.png"
    },
    {
      "title": "KPN",
      "category": "commercial",
      "type": "Commercial",
      "year": "2023",
      "vimeo_id": "817205311",
      "thumbnail": "assets/images/thumbnails/kpn.jpg",
      "credits": {
        "Director": "Jacobine van Hellemond",
        "Production": "hazazaH",
        "Agency": "dentsuACHTUNG!",
        "DOP": "Douwe Hennink",
        "Grade": "Joppo @ De Grot"
      },
      "thumbnail_url": "https://i.vimeocdn.com/video/2129059235-2768326689df68593bda0f3bf157eae3d724d2d7b3c5585aa9a0eece0b5554ee-d_640?region=us"
    },
    {
      "title": "Lapierre",
      "category": "commercial",
      "type": "Commercial",
      "year": "2022",
      "vimeo_id": "667685324",
      "thumbnail": "assets/images/thumbnails/lapierre.jpg",
      "credits": {
        "Director": "Ruben Van Leer",
        "Production": "Artillerie",
        "DOP": "Ezra Reverda",
        "Producer": "Philippe Avendaño Vera",
        "VFX": "Becanti Wijnbergh",
        "Grade": "Wietse van Bezooijen",
        "Online & Finishing": "The Compound",
        "Music": "Rimer London"
      },
      "thumbnail_url": "https://i.vimeocdn.com/video/2129051571-3beadb4cb4f7261b15b1b0988054102640768cc4505747d344b57089f8b0cedd-d_640?region=us"
    },
    {
      "title": "Scoon",
      "category": "commercial",
      "type": "Commercial",
      "year": "2022",
      "vimeo_id": "667726880",
      "thumbnail": "assets/images/thumbnails/scoon.jpg",
      "credits": {
        "Director": "Alexander Braam",
        "Production": "Mike Teevee",
        "DOP": "Myrthe Mosterman",
        "Grade": "Nick Sanders",
        "Sound": "Most"
      },
      "thumbnail_url": "https://i.vimeocdn.com/video/2129052604-d2fd2ae2e483f09112baea57ee45703dbd7842cd967146c01440cb10873a2021-d_640?region=us"
    },
    {
      "title": "Scotch & Soda",
      "category": "film",
      "type": "Fashion Film",
      "year": "2017",
      "vimeo_id": "238951610",
      "thumbnail": "assets/images/thumbnails/scotch-soda.jpg",
      "credits": {
        "Director": "Fleur Fortuné",
        "Agency": "133/Publicis Paris",
        "Creative Director": "Paulo Martins",
        "Producer": "Erika Vocking",
        "Music & Sound": "Massive Music",
        "Post Production": "The Ambassadors"
      },
      "thumbnail_url": "https://i.vimeocdn.com/video/2129060437-61a290458ebd9c8954eaa8df1ec4e58eda5b175a456154235de382dc2ab5d6c2-d_640?region=us"
    },
    {
      "title": "The Bird — Sing Me A Song",
      "category": "film",
      "type": "Short Film",
      "year": "2025",
      "vimeo_id": "1073863233",
      "thumbnail": "assets/images/thumbnails/the-bird.jpg",
      "credits": {
        "Director": "Ruben van Leer",
        "DOP": "Ezra Reverda",
        "Music": "Tigran Hamasyan",
        "Written by": "Philip M. Howe & Ruben van Leer",
        "Additional Editing": "Florian Millot & Ruben van Leer",
        "Grade": "Ruben Labree"
      },
      "thumbnail_url": "https://i.vimeocdn.com/video/2129047428-e4a60b9ad062d613af6e36e32c5dfbc49c9dba116259139d619ae299bf33832f-d_640?region=us"
    }
  ]
}
